geniusrise_text/__init__.py
geniusrise_text/base/__init__.py
geniusrise_text/base/api.py
geniusrise_text/base/bulk.py
geniusrise_text/base/communication.py
geniusrise_text/base/fine_tune.py
geniusrise_text/base/util.py
geniusrise_text/classification/__init__.py
geniusrise_text/classification/api.py
geniusrise_text/classification/bulk.py
geniusrise_text/classification/eval.py
geniusrise_text/classification/fine_tune.py
geniusrise_text/classification/tests/__init__.py
geniusrise_text/classification/tests/test_bulk.py
geniusrise_text/classification/tests/test_fine_tune.py
geniusrise_text/embeddings/__init__.py
geniusrise_text/embeddings/api.py
geniusrise_text/embeddings/bulk.py
geniusrise_text/embeddings/embeddings.py
geniusrise_text/embeddings/tests/__init__.py
geniusrise_text/embeddings/tests/test_bulk.py
geniusrise_text/embeddings/tests/test_embeddings.py
geniusrise_text/instruction/__init__.py
geniusrise_text/instruction/api.py
geniusrise_text/instruction/bulk.py
geniusrise_text/instruction/eval.py
geniusrise_text/instruction/fine_tune.py
geniusrise_text/instruction/tests/__init__.py
geniusrise_text/instruction/tests/test_bulk.py
geniusrise_text/instruction/tests/test_fine_tune.py
geniusrise_text/language_model/__init__.py
geniusrise_text/language_model/api.py
geniusrise_text/language_model/bulk.py
geniusrise_text/language_model/fine_tune.py
geniusrise_text/language_model/tests/__init__.py
geniusrise_text/language_model/tests/test_bulk.py
geniusrise_text/language_model/tests/test_fine_tune.py
geniusrise_text/ner/__init__.py
geniusrise_text/ner/api.py
geniusrise_text/ner/bulk.py
geniusrise_text/ner/fine_tune.py
geniusrise_text/ner/tests/__init__.py
geniusrise_text/ner/tests/test_fine_tune.py
geniusrise_text/nli/__init__.py
geniusrise_text/nli/api.py
geniusrise_text/nli/bulk.py
geniusrise_text/nli/fine_tune.py
geniusrise_text/nli/intents/__init__.py
geniusrise_text/nli/intents/artisan_marketplace.py
geniusrise_text/nli/intents/automotive.py
geniusrise_text-0.1.13.dist-info/LICENSE
geniusrise_text-0.1.13.dist-info/METADATA
geniusrise_text-0.1.13.dist-info/WHEEL
geniusrise_text-0.1.13.dist-info/top_level.txt
geniusrise_text-0.1.13.dist-info/RECORD
